{"0": "NuGet Test Spec", "1": "SQL DB and HTTP Server", "2": "Test NuGet Dependencies", "3": "MSSQLMcp NuGet Spec", "4": "PromptFlow Layout", "5": "MSSQLMcp Core Dependencies", "6": "Azure SDK Package Assets", "7": "Test Runtime Assemblies", "8": "MSSQLMcp Build Assets", "9": "Node MCP Server", "10": "Unit Test Suite", "11": "DotNet Project Config", "12": "Extensions Dependency Tree", "13": "PromptFlow AOAI Config", "14": "BCL Crypto Assets", "15": "TypeScript Config", "16": "Extensions Config Assets", "17": "Auth Environment Variables", "18": "Test Azure Identity", "19": "Test Extensions DI", "20": "SqlClient Locale Resources", "21": "Test SqlClient Locales", "22": "Extensions Config Primitives", "23": "Test Extensions Abstractions", "24": "Test Extensions Config", "25": "VSCode Agent Config", "26": "User Secrets Config", "27": "Config Binder Assets", "28": "Azure Identity Dependencies", "29": "Extensions Hosting Config", "30": "Test Project Assets", "31": "Test User Secrets", "32": "Test Config Binder", "33": "Test Azure Identity Assets", "34": "SqlClient SNI Runtime", "35": "README Samples Index", "36": "Extensions Config Abstractions", "37": "Env Vars Config Provider", "38": "DI Container Assets", "39": "Test Config Abstractions", "40": "Test Logging Abstractions", "41": "Test Extensions Config", "42": "Test Env Config Provider", "43": "Test Coverage Castle Core", "44": "Code Coverage Assets", "45": "Core DotNet Types", "46": "Java DevContainer", "47": "MSSQLMcp Project Assets", "48": "MSSQLMcp Compile Assets", "49": "Config CommandLine Provider", "50": "Config File Extensions", "51": "Config JSON Provider", "52": "DI Abstractions Assets", "53": "Diagnostics Abstractions", "54": "Diagnostics Assets", "55": "File Providers Abstractions", "56": "File Providers Physical", "57": "FileSystem Globbing", "58": "Hosting Abstractions", "59": "Hosting Assets", "60": "Package Asset 60", "61": "Package Asset 61", "62": "Package Asset 62", "63": "Package Asset 63", "64": "Package Asset 64", "65": "Package Asset 65", "66": "Package Asset 66", "67": "Package Asset 67", "68": "Package Asset 68", "69": "Package Asset 69", "70": "Package Asset 70", "71": "Package Asset 71", "72": "Package Asset 72", "73": "Package Asset 73", "74": "Package Asset 74", "75": "Package Asset 75", "76": "Package Asset 76", "77": "Package Asset 77", "78": "Package Asset 78", "79": "Package Asset 79", "80": "Package Asset 80", "81": "Package Asset 81", "82": "Package Asset 82", "83": "Package Asset 83", "84": "Package Asset 84", "85": "Package Asset 85", "86": "Package Asset 86", "87": "Package Asset 87", "88": "Package Asset 88", "89": "Package Asset 89", "90": "Package Asset 90", "91": "Package Asset 91", "92": "Package Asset 92", "93": "Package Asset 93", "94": "Package Asset 94", "95": "Package Asset 95", "96": "Package Asset 96", "97": "Package Asset 97", "98": "Package Asset 98", "99": "Package Asset 99", "100": "Package Asset 100", "101": "Package Asset 101", "102": "Package Asset 102", "103": "Package Asset 103", "104": "Package Asset 104", "105": "Package Asset 105", "106": "Package Asset 106", "107": "Package Asset 107", "108": "Package Asset 108", "109": "Package Asset 109", "110": "Package Asset 110", "111": "Package Asset 111", "112": "Package Asset 112", "113": "Package Asset 113", "114": "Package Asset 114", "115": "Package Asset 115", "116": "Package Asset 116", "117": "Package Asset 117", "118": "Package Asset 118", "119": "Package Asset 119", "120": "Package Asset 120", "121": "Package Asset 121", "122": "Package Asset 122", "123": "Package Asset 123", "124": "Package Asset 124", "125": "Package Asset 125", "126": "Package Asset 126", "127": "Package Asset 127", "128": "Package Asset 128", "129": "Package Asset 129", "130": "Package Asset 130", "131": "Package Asset 131", "132": "Package Asset 132", "133": "Package Asset 133", "134": "Package Asset 134", "135": "Package Asset 135", "136": "Package Asset 136", "137": "Package Asset 137", "138": "Package Asset 138", "139": "Package Asset 139", "140": "Package Asset 140", "141": "Package Asset 141", "142": "Package Asset 142", "143": "Package Asset 143", "144": "Package Asset 144", "145": "Package Asset 145", "146": "Package Asset 146", "147": "Package Asset 147", "148": "Package Asset 148", "149": "Package Asset 149", "150": "Package Asset 150", "151": "Package Asset 151", "152": "Package Asset 152", "153": "Package Asset 153", "154": "Package Asset 154", "155": "Package Asset 155", "156": "Package Asset 156", "157": "Package Asset 157", "158": "Package Asset 158", "159": "Package Asset 159", "160": "Package Asset 160", "161": "Package Asset 161", "162": "Package Asset 162", "163": "Package Asset 163"}